french_public_holidays/__init__.py
french_public_holidays/__main__.py
french_public_holidays/config_manager.py
french_public_holidays/exceptions.py
french_public_holidays/french_public_holidays.py
french_public_holidays/output.py
french_public_holidays/settings.py
french_public_holidays-0.5.8.dist-info/LICENSE
french_public_holidays-0.5.8.dist-info/METADATA
french_public_holidays-0.5.8.dist-info/WHEEL
french_public_holidays-0.5.8.dist-info/entry_points.txt
french_public_holidays-0.5.8.dist-info/top_level.txt
french_public_holidays-0.5.8.dist-info/RECORD
