Metadata-Version: 2.2
Name: french_public_holidays
Version: 0.5.8
Summary: Get French public holidays from the French government API
Home-page: https://github.com/tsnaketech/french-public-holidays
Author: SnakeTech
Author-email: repo@snaketech.net
License: MIT
Project-URL: Source, https://github.com/tsnaketech/french-public-holidays
Project-URL: Issues, https://github.com/tsnaketech/french-public-holidays/issues
Classifier: Intended Audience :: Developers
Classifier: License :: OSI Approved :: MIT License
Classifier: Natural Language :: English
Classifier: Natural Language :: French
Classifier: Programming Language :: Python :: 3.11
Classifier: Programming Language :: Python :: 3.12
License-File: LICENSE
Requires-Dist: configparser
Requires-Dist: httpx
Requires-Dist: pydantic
Requires-Dist: python-dotenv
Requires-Dist: PyYAML
Dynamic: author
Dynamic: author-email
Dynamic: classifier
Dynamic: description
Dynamic: description-content-type
Dynamic: home-page
Dynamic: license
Dynamic: project-url
Dynamic: requires-dist
Dynamic: summary
